args_me_model/__init__.py
args_me_model/claim.py
args_me_model/claim_id.py
args_me_model/source.py
args_me_model/support.py
args_me_model-0.4.1.dist-info/LICENSE
args_me_model-0.4.1.dist-info/METADATA
args_me_model-0.4.1.dist-info/WHEEL
args_me_model-0.4.1.dist-info/top_level.txt
args_me_model-0.4.1.dist-info/RECORD
