Metadata-Version: 2.2
Name: args-me-model
Version: 0.4.1
Summary: Data model for the args.me argument search engine
Author: Johannes Kiesel
Maintainer: Johannes Kiesel
License: MIT License
Project-URL: Homepage, https://webis.de/args-me-model/
Project-URL: Documentation, https://webis.de/args-me-model/
Project-URL: Source, https://github.com/webis-de/args-me-model
Project-URL: Issues, https://github.com/webis-de/args-me-model/issues
Keywords: argumentation
Requires-Python: >=3.10
License-File: LICENSE
Requires-Dist: pydantic>=2.10.6
